aminodorks/__init__.py
aminodorks/_client.py
aminodorks/_community.py
aminodorks/arcana/__init__.py
aminodorks/arcana/_elder_crypt.py
aminodorks/arcana/_headers_manager.py
aminodorks/arcana/_helpers.py
aminodorks/arcana/_relay_client.py
aminodorks/citadel/__init__.py
aminodorks/citadel/_auth.py
aminodorks/citadel/_link.py
aminodorks/citadel/_media.py
aminodorks/citadel/_space.py
aminodorks/citadel/_thread.py
aminodorks/citadel/_user.py
aminodorks/glyphs/__init__.py
aminodorks/glyphs/_additional.py
aminodorks/glyphs/_auth_glyph.py
aminodorks/glyphs/_comment_glyph.py
aminodorks/glyphs/_community_glyph.py
aminodorks/glyphs/_message_glyph.py
aminodorks/glyphs/_sid.py
aminodorks/glyphs/_thread_glyph.py
aminodorks-0.6.0.dist-info/METADATA
aminodorks-0.6.0.dist-info/WHEEL
aminodorks-0.6.0.dist-info/top_level.txt
aminodorks-0.6.0.dist-info/RECORD
