Metadata-Version: 2.4
Name: AminoDorks
Version: 0.6.0
Summary: AminoDorksPY is a Python library that interacts with the AminoApps API.
Author-email: Nullable-developer <work.email.none@gmail.com>
Keywords: amino,api,client,community
Classifier: Programming Language :: Python :: 3
Classifier: License :: OSI Approved :: MIT License
Classifier: Operating System :: OS Independent
Requires-Python: >=3.10
Requires-Dist: aiohttp>=3.12.15
Requires-Dist: aiofiles>=24.1.0
Requires-Dist: msgspec>=0.19.0
